LICENSE
MANIFEST.in
README.md
setup.cfg
setup.py
livereload/__init__.py
livereload/cli.py
livereload/handlers.py
livereload/server.py
livereload/watcher.py
livereload/management/commands/__init__.py
livereload/management/commands/livereload.py
livereload/vendors/livereload.js
livereloadx.egg-info/PKG-INFO
livereloadx.egg-info/SOURCES.txt
livereloadx.egg-info/dependency_links.txt
livereloadx.egg-info/entry_points.txt
livereloadx.egg-info/requires.txt
livereloadx.egg-info/top_level.txt
tests/test_watcher.py